de/__init__.py
de/p1st/__init__.py
de/p1st/monitor/__init__.py
de/p1st/monitor/csv_util.py
de/p1st/monitor/datetime_util.py
de/p1st/monitor/exec_capture.py
de/p1st/monitor/logger.py
de/p1st/monitor/logger_ex.py
de/p1st/monitor/main.py
de/p1st/monitor/print_util.py
de/p1st/monitor/string_conversion.py
de/p1st/monitor/warn.py
de/p1st/monitor/warn_data.py
de/p1st/monitor/cfg/__init__.py
de/p1st/monitor/cfg/loggers.py
de/p1st/monitor/cfg/logging_dir.py
de/p1st/monitor/cfg/singleton.py
de/p1st/monitor/loggers/__init__.py
de/p1st/monitor/loggers/cpu.py
de/p1st/monitor/loggers/drive.py
de/p1st/monitor/loggers/drive_temp.py
de/p1st/monitor/loggers/filesystem.py
de/p1st/monitor/loggers/memory.py
de/p1st/monitor/loggers/network.py
de/p1st/monitor/loggers/sensor_script.py
de/p1st/monitor/loggers/swap.py
de/p1st/monitor/loggers/temp.py
de.p1st.monitor-0.13.0.dist-info/LICENSE
de.p1st.monitor-0.13.0.dist-info/METADATA
de.p1st.monitor-0.13.0.dist-info/WHEEL
de.p1st.monitor-0.13.0.dist-info/entry_points.txt
de.p1st.monitor-0.13.0.dist-info/top_level.txt
de.p1st.monitor-0.13.0.dist-info/RECORD
