Metadata-Version: 2.1
Name: de.p1st.monitor
Version: 0.13.0
Summary: periodically monitor and warn
Home-page: https://codeberg.org/privacy1st/de-p1st-monitor
Author: Daniel Langbein
Author-email: daniel@systemli.org
Project-URL: Bug Tracker, https://codeberg.org/privacy1st/de-p1st-monitor/issues
Classifier: Development Status :: 4 - Beta
Classifier: Programming Language :: Python :: 3
Classifier: Operating System :: Unix
Requires-Python: >=3.10.0
License-File: LICENSE
